COPYING
Developers.md
HISTORY.md
MANIFEST.in
README.md
dev-requirements.txt
pre-commit.sh
requirements.txt
setup.cfg
setup.py
bin/build_sphinx_docs.py
bin/ipynb2rst.py
bin/run_docs_server.py
coral/__init__.py
coral.egg-info/PKG-INFO
coral.egg-info/SOURCES.txt
coral.egg-info/dependency_links.txt
coral.egg-info/not-zip-safe
coral.egg-info/requires.txt
coral.egg-info/top_level.txt
coral/analysis/__init__.py
coral/analysis/utils.py
coral/analysis/_sequence/__init__.py
coral/analysis/_sequence/anneal.py
coral/analysis/_sequence/melting_temp.py
coral/analysis/_sequence/repeats.py
coral/analysis/_sequence/tm_params.py
coral/analysis/_sequencing/__init__.py
coral/analysis/_sequencing/align.py
coral/analysis/_sequencing/calign.c
coral/analysis/_sequencing/calign.pyx
coral/analysis/_sequencing/mafft.py
coral/analysis/_sequencing/needle.py
coral/analysis/_sequencing/sanger.py
coral/analysis/_sequencing/substitution_matrices.py
coral/analysis/_structure/__init__.py
coral/analysis/_structure/dimers.py
coral/analysis/_structure/nupack.py
coral/analysis/_structure/structure_analyzer.py
coral/analysis/_structure/structure_windows.py
coral/analysis/_structure/viennarna.py
coral/constants/__init__.py
coral/constants/genbank.py
coral/constants/molecular_bio.py
coral/constants/restriction_sites.py
coral/database/__init__.py
coral/database/_entrez.py
coral/database/_rebase.py
coral/database/_yeast.py
coral/design/__init__.py
coral/design/_gibson.py
coral/design/_primers.py
coral/design/_oligo_synthesis/__init__.py
coral/design/_oligo_synthesis/oligo_assembly.py
coral/design/_sequence_generation/__init__.py
coral/design/_sequence_generation/random_sequences.py
coral/reaction/__init__.py
coral/reaction/_central_dogma.py
coral/reaction/_gibson.py
coral/reaction/_oligo_assembly.py
coral/reaction/_pcr.py
coral/reaction/_resect.py
coral/reaction/_restriction.py
coral/reaction/utils.py
coral/seqio/__init__.py
coral/seqio/_dna.py
coral/sequence/__init__.py
coral/sequence/_dna.py
coral/sequence/_nucleicacid.py
coral/sequence/_peptide.py
coral/sequence/_rna.py
coral/sequence/_sequence.py
coral/sequence/d3-plasmid.js
coral/utils/__init__.py
coral/utils/tempdirs.py
