Metadata-Version: 1.1
Name: coral
Version: 0.5.0
Summary: Coral: code-ify your synthetic DNA design workflow.
Home-page: https://github.com/klavinslab/coral
Author: Nick Bolten
Author-email: nbolten _at_ gmail
License: MIT
Download-URL: https://github.com/klavinslab/coral.git
Keywords: synthetic biology,biology,design,automation,cloning,sanger,primer,dna,structure
Platform: UNKNOWN
Classifier: Programming Language :: Python
Classifier: Programming Language :: Python :: 2.7
Classifier: Programming Language :: Python :: 2 :: Only
Classifier: Topic :: Scientific/Engineering
Classifier: Topic :: Scientific/Engineering :: Bio-Informatics
